./.gitattributes
./.gitignore
./CODE_OF_CONDUCT.md
./CONTRIBUTING.md
./LICENSE
./PKG-INFO
./README.md
./cookiecutter.json
./pyproject.toml
./hooks/post_gen_project.py
./{{cookiecutter.project_name}}/.cookiecutter.json
./{{cookiecutter.project_name}}/.editorconfig
./{{cookiecutter.project_name}}/.gitattributes
./{{cookiecutter.project_name}}/.gitignore
./{{cookiecutter.project_name}}/.pre-commit-config.yaml
./{{cookiecutter.project_name}}/.readthedocs.yml
./{{cookiecutter.project_name}}/CODE_OF_CONDUCT.md
./{{cookiecutter.project_name}}/CONTRIBUTING.md
./{{cookiecutter.project_name}}/README.md
./{{cookiecutter.project_name}}/codecov.yml
./{{cookiecutter.project_name}}/noxfile.py
./{{cookiecutter.project_name}}/pyproject.toml
./{{cookiecutter.project_name}}/{% if cookiecutter.license == 'Apache-2.0' -%} LICENSE {%- endif %}
./{{cookiecutter.project_name}}/{% if cookiecutter.license == 'GPL-3.0' -%} LICENSE {%- endif %}
./{{cookiecutter.project_name}}/{% if cookiecutter.license == 'MIT' -%} LICENSE {%- endif %}
./{{cookiecutter.project_name}}/.github/dependabot.yml
./{{cookiecutter.project_name}}/.github/labels.yml
./{{cookiecutter.project_name}}/.github/release-drafter.yml
./{{cookiecutter.project_name}}/.github/workflows/constraints.txt
./{{cookiecutter.project_name}}/.github/workflows/labeler.yml
./{{cookiecutter.project_name}}/.github/workflows/release.yml
./{{cookiecutter.project_name}}/.github/workflows/tests.yml
./{{cookiecutter.project_name}}/docs/codeofconduct.md
./{{cookiecutter.project_name}}/docs/conf.py
./{{cookiecutter.project_name}}/docs/contributing.md
./{{cookiecutter.project_name}}/docs/index.md
./{{cookiecutter.project_name}}/docs/license.md
./{{cookiecutter.project_name}}/docs/reference.md
./{{cookiecutter.project_name}}/docs/requirements.txt
./{{cookiecutter.project_name}}/docs/usage.md
./{{cookiecutter.project_name}}/src/{{cookiecutter.package_name}}/__init__.py
./{{cookiecutter.project_name}}/src/{{cookiecutter.package_name}}/__main__.py
cookiecutter_uv_hypermodern_python-2025.6.26.dist-info/METADATA
cookiecutter_uv_hypermodern_python-2025.6.26.dist-info/WHEEL
cookiecutter_uv_hypermodern_python-2025.6.26.dist-info/entry_points.txt
cookiecutter_uv_hypermodern_python-2025.6.26.dist-info/licenses/LICENSE
cookiecutter_uv_hypermodern_python-2025.6.26.dist-info/RECORD
