Metadata-Version: 2.4
Name: cookiecutter-uv-hypermodern-python
Version: 2025.6.26
Summary: A Cookiecutter template for a hypermodern Python project using uv.
Project-URL: Homepage, https://github.com/bosd/cookiecutter-uv-hypermodern-python
Project-URL: Repository, https://github.com/bosd/cookiecutter-uv-hypermodern-python
Project-URL: Documentation, https://cookiecutter-uv-hypermodern-python.readthedocs.io/
Project-URL: Changelog, https://github.com/bosd/cookiecutter-uv-hypermodern-python/releases
Author-email: bosd <c5e2fd43-d292-4c90-9d1f-74ff3436329a@anonaddy.me>
License-Expression: MIT
License-File: LICENSE
Classifier: Development Status :: 4 - Beta
Classifier: Intended Audience :: Developers
Classifier: Programming Language :: Python :: 3
Classifier: Programming Language :: Python :: 3.9
Classifier: Programming Language :: Python :: 3.10
Classifier: Programming Language :: Python :: 3.11
Classifier: Programming Language :: Python :: 3.12
Classifier: Programming Language :: Python :: 3.13
Classifier: Topic :: Software Development :: Build Tools
Classifier: Topic :: Software Development :: Code Generators
Classifier: Topic :: Software Development :: Libraries :: Python Modules
Requires-Python: >=3.9
Requires-Dist: click>=8.0.1
